ds_common_tool/__init__.py
ds_common_tool/data_utils.py
ds_common_tool/shandong.py
ds_common_tool/shanxi.py
ds_common_tool/suite_base.py
ds_common_tool/suite_class_entry.py
ds_common_tool/suite_data.py
ds_common_tool/suite_feature_engineer_sg.py
ds_common_tool/suite_feature_engineer_tt.py
ds_common_tool/suite_model.py
ds_common_tool/usep_long.py
ds_common_tool/usep_short.py
ds_common_tool-0.2.57.dist-info/METADATA
ds_common_tool-0.2.57.dist-info/WHEEL
ds_common_tool-0.2.57.dist-info/top_level.txt
ds_common_tool-0.2.57.dist-info/RECORD
